setup.py
try_pypi_202009/Binomialdistribution.py
try_pypi_202009/Gaussiandistribution.py
try_pypi_202009/Generaldistribution.py
try_pypi_202009/__init__.py
try_pypi_202009.egg-info/PKG-INFO
try_pypi_202009.egg-info/SOURCES.txt
try_pypi_202009.egg-info/dependency_links.txt
try_pypi_202009.egg-info/not-zip-safe
try_pypi_202009.egg-info/top_level.txt