Metadata-Version: 1.0
Name: try-pypi-202009
Version: 0.1
Summary: Try upload a package to pypi
Home-page: UNKNOWN
Author: udacity
Author-email: UNKNOWN
License: UNKNOWN
Platform: UNKNOWN
